pigment64-0.6.3.dist-info/METADATA
pigment64-0.6.3.dist-info/WHEEL
pigment64-0.6.3.dist-info/licenses/LICENSE
pigment64/__init__.py
pigment64/pigment64.cpython-313t-arm-linux-gnueabihf.so
pigment64-0.6.3.dist-info/RECORD
