Metadata-Version: 2.4
Name: pigment64
Version: 0.6.3
Classifier: Programming Language :: Rust
Classifier: Programming Language :: Python :: Implementation :: CPython
Classifier: Programming Language :: Python :: Implementation :: PyPy
License-File: LICENSE
Summary: A library for handling conversion between N64 texture formats and modern image formats
Requires-Python: >=3.9
Project-URL: Repository, https://github.com/decompals/pigment64
Project-URL: Bug Tracker, https://github.com/decompals/pigment64/issues
